quilter/__init__.py
quilter/_functions.py
quilter-0.0.3.dist-info/LICENSE
quilter-0.0.3.dist-info/METADATA
quilter-0.0.3.dist-info/WHEEL
quilter-0.0.3.dist-info/top_level.txt
quilter-0.0.3.dist-info/RECORD
