Metadata-Version: 2.1
Name: quilter
Version: 0.0.3
Summary: Python implementation of the R package patchwork, but for Matplotlib
Home-page: https://github.com/bbcho/quilter-dev
Author: Ben Cho
Author-email: ben.cho@gmail.com
License: MIT License
Keywords: quilter,patchwork,matplotlib,plot,compose
Platform: UNKNOWN
Classifier: Development Status :: 3 - Alpha
Classifier: License :: OSI Approved :: MIT License
Classifier: Programming Language :: Python :: 3
Classifier: Operating System :: OS Independent
Requires-Python: >=3.6
Requires-Dist: matplotlib
